location_util/__init__.py
location_util/china_location.txt
location_util/china_location_change.txt
location_util/dictionary_loader.py
location_util/location_parser.py
location_parse_xl-0.0.5.dist-info/METADATA
location_parse_xl-0.0.5.dist-info/WHEEL
location_parse_xl-0.0.5.dist-info/top_level.txt
location_parse_xl-0.0.5.dist-info/RECORD
